modin-autoimport-pandas.pth
modin/__init__.py
modin/__main__.py
modin/_version.py
modin/conftest.py
modin/db_conn.py
modin/error_message.py
modin/utils.py
modin/config/__init__.py
modin/config/__main__.py
modin/config/envvars.py
modin/config/pubsub.py
modin/core/__init__.py
modin/core/computation/__init__.py
modin/core/computation/align.py
modin/core/computation/check.py
modin/core/computation/common.py
modin/core/computation/engines.py
modin/core/computation/eval.py
modin/core/computation/expr.py
modin/core/computation/ops.py
modin/core/computation/parsing.py
modin/core/computation/scope.py
modin/core/dataframe/__init__.py
modin/core/dataframe/algebra/__init__.py
modin/core/dataframe/algebra/binary.py
modin/core/dataframe/algebra/fold.py
modin/core/dataframe/algebra/groupby.py
modin/core/dataframe/algebra/map.py
modin/core/dataframe/algebra/operator.py
modin/core/dataframe/algebra/reduce.py
modin/core/dataframe/algebra/tree_reduce.py
modin/core/dataframe/algebra/default2pandas/__init__.py
modin/core/dataframe/algebra/default2pandas/binary.py
modin/core/dataframe/algebra/default2pandas/cat.py
modin/core/dataframe/algebra/default2pandas/dataframe.py
modin/core/dataframe/algebra/default2pandas/datetime.py
modin/core/dataframe/algebra/default2pandas/default.py
modin/core/dataframe/algebra/default2pandas/groupby.py
modin/core/dataframe/algebra/default2pandas/list.py
modin/core/dataframe/algebra/default2pandas/resample.py
modin/core/dataframe/algebra/default2pandas/rolling.py
modin/core/dataframe/algebra/default2pandas/series.py
modin/core/dataframe/algebra/default2pandas/str.py
modin/core/dataframe/algebra/default2pandas/struct.py
modin/core/dataframe/base/__init__.py
modin/core/dataframe/base/dataframe/__init__.py
modin/core/dataframe/base/dataframe/dataframe.py
modin/core/dataframe/base/dataframe/utils.py
modin/core/dataframe/base/interchange/__init__.py
modin/core/dataframe/base/interchange/dataframe_protocol/__init__.py
modin-0.37.1.dist-info/LICENSE
modin-0.37.1.dist-info/LICENSE_HEADER
modin-0.37.1.dist-info/METADATA
modin-0.37.1.dist-info/NOTICE
modin-0.37.1.dist-info/WHEEL
modin-0.37.1.dist-info/top_level.txt
modin-0.37.1.dist-info/RECORD
