Metadata-Version: 2.1
Name: modin
Version: 0.37.1
Summary: Modin: Make your pandas code run faster by changing one line of code.
Home-page: https://github.com/modin-project/modin
License: Apache 2
Platform: UNKNOWN
Requires-Python: >=3.9
License-File: LICENSE
License-File: LICENSE_HEADER
License-File: NOTICE
Requires-Dist: pandas<2.4,>=2.2
Requires-Dist: packaging>=21.0
Requires-Dist: numpy>=1.22.4
Requires-Dist: fsspec>=2022.11.0
Requires-Dist: psutil>=5.8.0
Requires-Dist: typing-extensions
Provides-Extra: all
Requires-Dist: dask>=2.22.0; extra == "all"
Requires-Dist: distributed>=2.22.0; extra == "all"
Requires-Dist: ray<3,>=2.10.0; extra == "all"
Requires-Dist: pyarrow>=10.0.1; extra == "all"
Requires-Dist: modin-spreadsheet>=0.1.0; extra == "all"
Requires-Dist: dataframe-api-compat>=0.2.7; extra == "all"
Provides-Extra: consortium-standard
Requires-Dist: dataframe-api-compat>=0.2.7; extra == "consortium-standard"
Provides-Extra: dask
Requires-Dist: dask>=2.22.0; extra == "dask"
Requires-Dist: distributed>=2.22.0; extra == "dask"
Provides-Extra: mpi
Requires-Dist: unidist[mpi]>=0.2.1; extra == "mpi"
Provides-Extra: ray
Requires-Dist: ray<3,>=2.10.0; extra == "ray"
Requires-Dist: pyarrow>=10.0.1; extra == "ray"
Provides-Extra: spreadsheet
Requires-Dist: modin-spreadsheet>=0.1.0; extra == "spreadsheet"
